spec/__init__.py
spec/_version.py
spec/cli.py
spec/plugin.py
spec/trap.py
spec/utils.py
spec-1.4.1.dist-info/dependency_links.txt
spec-1.4.1.dist-info/DESCRIPTION.rst
spec-1.4.1.dist-info/entry_points.txt
spec-1.4.1.dist-info/METADATA
spec-1.4.1.dist-info/metadata.json
spec-1.4.1.dist-info/RECORD
spec-1.4.1.dist-info/top_level.txt
spec-1.4.1.dist-info/WHEEL
