Metadata-Version: 2.0
Name: spec
Version: 1.4.1
Summary: Specification-style output for nose
Home-page: https://github.com/bitprophet/spec
Author: Jeff Forcier
Author-email: jeff@bitprophet.org
License: MIT
Platform: UNKNOWN
Classifier: Development Status :: 4 - Beta
Classifier: Environment :: Plugins
Classifier: Intended Audience :: Developers
Classifier: License :: OSI Approved :: MIT License
Classifier: Programming Language :: Python
Classifier: Programming Language :: Python :: 2.6
Classifier: Programming Language :: Python :: 2.7
Classifier: Programming Language :: Python :: 3.3
Classifier: Topic :: Software Development :: Testing
Requires-Dist: nose (>=1.3,<2.0)
Requires-Dist: six (<2.0)
